[
  {
    "name" : "League of Legends",
    "imageName" : "lol",
    "id": 1
  },
  {
    "name" : "Minecraft",
    "imageName" : "minecraft",
    "id" : 2
  },
  {
    "name" : "League of Legends",
    "imageName" : "lol",
    "id": 1
  },
  {
    "name" : "Minecraft",
    "imageName" : "minecraft",
    "id" : 2
  },
  {
    "name" : "League of Legends",
    "imageName" : "lol",
    "id": 1
  },
  {
    "name" : "Minecraft",
    "imageName" : "minecraft",
    "id" : 2
  },
  {
    "name" : "League of Legends",
    "imageName" : "lol",
    "id": 1
  },
  {
    "name" : "Minecraft",
    "imageName" : "minecraft",
    "id" : 2
  },
  {
    "name" : "League of Legends",
    "imageName" : "lol",
    "id": 1
  },
  {
    "name" : "Minecraft",
    "imageName" : "minecraft",
    "id" : 2
  },
  
]
